src/main.py
qm_lib-0.0.1.dist-info/METADATA
qm_lib-0.0.1.dist-info/WHEEL
qm_lib-0.0.1.dist-info/licenses/LICENSE
qm_lib-0.0.1.dist-info/RECORD
