Metadata-Version: 2.3
Name: Qm-lib
Version: 0.0.1
Summary: A small example package
Project-URL: Homepage, https://gitee.com/xiatian0716/Qm-lib
Project-URL: Bug Tracker, https://gitee.com/xiatian0716/Qm-lib/issues
Author-email: xiatian0716 <819337877@qq.com>
License-File: LICENSE
Classifier: License :: OSI Approved :: MIT License
Classifier: Operating System :: OS Independent
Classifier: Programming Language :: Python :: 3
Requires-Python: >=3.7
